OneKeyTcn/IdentifyURLUtil.py
OneKeyTcn/OKTcn.py
OneKeyTcn/RedirectUtil.py
OneKeyTcn/__init__.py
OneKeyTcn/core_api_sina.py
OneKeyTcn/core_api_txapi.py
OneKeyTcn/core_api_xiaomark.py
OKTcn-2.3.4.dist-info/METADATA
OKTcn-2.3.4.dist-info/WHEEL
OKTcn-2.3.4.dist-info/top_level.txt
OKTcn-2.3.4.dist-info/RECORD
