Metadata-Version: 2.1
Name: OKTcn
Version: 2.3.4
Summary: v2.3.4：timeout 3-5  并且增加小马补偿机制
Home-page: https://bitbucket.org/pyers/dancewithpy/src/master/Tcn/
Author: AlaricNorris
Author-email: norris.sly@gmail.com
Maintainer: AlaricNorris
Maintainer-email: norris.sly@gmail.com
License: BSD License
Platform: all
Classifier: Development Status :: 4 - Beta
Classifier: Operating System :: OS Independent
Classifier: Intended Audience :: Developers
Classifier: License :: OSI Approved :: BSD License
Classifier: Programming Language :: Python
Classifier: Programming Language :: Python :: Implementation
Classifier: Programming Language :: Python :: 2
Classifier: Programming Language :: Python :: 2.7
Classifier: Programming Language :: Python :: 3
Classifier: Programming Language :: Python :: 3.4
Classifier: Programming Language :: Python :: 3.5
Classifier: Programming Language :: Python :: 3.6
Classifier: Topic :: Software Development :: Libraries
Requires-Dist: requests (>=2.19.1)
Requires-Dist: NorrisUtils (>=0.5.2)
